mlox/__init__.py
mlox/__main__.py
mlox/configHandler.py
mlox/fileFinder.py
mlox/loadOrder.py
mlox/pluggraph.py
mlox/qtGui.py
mlox/resources.py
mlox/ruleParser.py
mlox/translations.py
mlox/update.py
mlox/version.py
mlox/static/__init__.py
mlox/static/mlox.gif
mlox/static/mlox.ico
mlox/static/mlox.msg
mlox/static/window.qml
mlox-1.0.3.dist-info/LICENSE.txt
mlox-1.0.3.dist-info/METADATA
mlox-1.0.3.dist-info/WHEEL
mlox-1.0.3.dist-info/entry_points.txt
mlox-1.0.3.dist-info/top_level.txt
mlox-1.0.3.dist-info/RECORD
