Metadata-Version: 2.1
Name: mlox
Version: 1.0.3
Summary: A tool for analyzing and sorting your Morrowind plugin load order.
Home-page: https://github.com/mlox/mlox
Author: Arthur Moore
Author-email: AMoore-pip@cd-net.net
License: UNKNOWN
Keywords: Morrowind Modding
Platform: UNKNOWN
Classifier: Intended Audience :: End Users/Desktop
Classifier: License :: OSI Approved :: MIT License
Classifier: Operating System :: OS Independent
Classifier: Topic :: Games/Entertainment
Requires-Python: >=3.5
Requires-Dist: colorama
Requires-Dist: appdirs
Requires-Dist: pyqt5
Requires-Dist: py7zr
